<?xml version="1.0" encoding="utf-8"?>
<resources>
	<string name='key1'>값1</string>
	<string name='key2'>값2</string>
	<string name='key3'>값3</string>
	<string name='key4'>값4</string>
	<string name='key5'>값5</string>
	<string name='key6'>값6</string>
	<string name='key7'>값7</string>
	<string name='key8'>값8</string>
	<string name='key9'>값9</string>
	<string name='key10'>값10</string>
	<string name='key11'>값11</string>
	<string name='key12'>값12</string>
	<string name='key13'>값13</string>
	<string name='key14'>값14</string>
	<string name='key15'>값15</string>
	<string name='key16'>값16</string>
	<string name='key17'>값17</string>
	<string name='key18'>값18</string>
	<string name='key19'>값19</string>
	<string name='key20'>값20</string>
	<string name='key21'>값21</string>
	<string name='key22'>값22</string>
	<string name='key23'>값23</string>
	<string name='key24'>값24</string>
	<string name='key25'>값25</string>
	<string name='key26'>값26</string>
	<string name='key27'>값27</string>
	<string name='key28'>값28</string>
	<string name='key29'>값29</string>
	<string name='key30'>값30</string>
	<string name='key31'>값31</string>
	<string name='key32'>값32</string>
	<string name='key33'>값33</string>
	<string name='key34'>값34</string>
	<string name='key35'>값35</string>
	<string name='key36'>값36</string>
	<string name='key37'>값37</string>
	<string name='key38'>값38</string>
</resources>